{
  "name": "Keepcalm",
  "type": "dark",
  "colors": {
    "foreground": "#E7E8EA",
    "editor.background": "#1d191a",
    "editor.foldBackground": "#1d191a",
    "tab.activeBackground": "#1d191a",
    "tab.activeForeground": "#E7E8EA",
    "tab.inactiveBackground": "#2e2c2d",
    "tab.inactiveForeground": "#6e7681",
    "titleBar.activeBackground": "#1d191a",
    "titleBar.inactiveBackground": "#1d191a",
    "activityBarBadge.background": "#1d191a",
    "sideBar.background": "#1d191a",
    "sideBar.foreground": "#6e7681",
    "sideBarSectionHeader.foreground": "#A3ABB5",
    "sideBarSectionHeader.background": "#1d191a",
    "activityBar.background": "#1d191a",
    "activityBar.foreground": "#E7E8EA",
    "activityBar.activeBorder": "#E7E8EA",
    "activityBar.inactiveForeground": "#6e7681",
    "statusBar.background": "#1d191a",
    "statusBar.foreground": "#6e7681",
    "statusBarItem.hoverBackground": "#1d191a",
    "statusBarItem.activeBackground": "#191517",
    "editorRuler.foreground": "#2a2d31",
    "editorLineNumber.foreground": "#3e4651",
    "list.activeSelectionForeground": "#E7E8EA",
    "list.activeSelectionBackground": "#2e2c2d",
    "list.focusOutline": "#3d444e",
    "list.focusBackground": "#2e2c2d",
    "list.inactiveSelectionBackground": "#1d191a",
    "list.inactiveSelectionForeground": "#E7E8EA",
    "list.hoverBackground": "#2e2c2d",
    "list.hoverForeground": "#a7a8aA",
    "editor.lineHighlightBackground": "#2e2c2d",
    "editor.lineHighlightBorder": "#3d444e"
  },
  "tokenColors": [
    {
      "name": "Comment",
      "scope": ["comment", "punctuation.definition.comment"],
      "settings": {
        "fontStyle": "italic",
        "foreground": "#6e7681"
      }
    },
    {
      "name": "Variables / Constants",
      "scope": [
        "variable",
        "constant.other.color",
        "string constant.other.placeholder",
        "constant.language",
        "keyword.operator.assignment",
        "keyword.operator.optional",
        "keyword.operator.spread"
      ],
      "settings": {
        "foreground": "#E7E8EA"
      }
    },
    {
      "name": "Keywords",
      "scope": ["keyword"],
      "settings": {
        "foreground": "#e7809c"
      }
    },
    {
      "name": "Storage",
      "scope": ["storage"],
      "settings": {
        "foreground": "#549bb1"
      }
    },
    {
      "name": "Strings",
      "scope": ["string"],
      "settings": {
        "fontStyle": "italic",
        "foreground": "#7fac82"
      }
    },
    {
      "name": "Types",
      "scope": ["entity.name.type", "support.type"],
      "settings": {
        "foreground": "#dfaf79"
      }
    },
    {
      "name": "Object members",
      "scope": [
        "meta.object.member",
        "entity.other.attribute-name",
        "variable.parameter"
        // "variable.other.object.property",
        // "variable.other.property"
      ],
      "settings": {
        "foreground": "#99b1b1"
      }
    },
    {
      "name": "Functions",
      "scope": ["entity.name.function"],
      "settings": {
        "foreground": "#d4c79a"
      }
    },
    {
      "name": "Entities",
      "scope": [
        "meta.definition.variable",
        "punctuation.definition.tag",
        "entity.name"
      ],
      "settings": {
        "foreground": "#66c9a3"
      }
    }
  ]
}
